{
 "actions": [],
 "creation": "2026-05-19 00:00:00.000000",
 "doctype": "DocType",
 "document_type": "Other",
 "editable_grid": 1,
 "engine": "InnoDB",
 "field_order": [
  "customer",
  "customer_name",
  "business_legal_name",
  "client_code",
  "customer_status"
 ],
 "fields": [
  {
   "fieldname": "customer",
   "fieldtype": "Link",
   "in_list_view": 1,
   "label": "Customer",
   "options": "Customer",
   "reqd": 1
  },
  {
   "fetch_from": "customer.customer_name",
   "fieldname": "customer_name",
   "fieldtype": "Data",
   "in_list_view": 1,
   "label": "Customer Name",
   "read_only": 1
  },
  {
   "fetch_from": "customer.business_legal_name",
   "fieldname": "business_legal_name",
   "fieldtype": "Data",
   "label": "Business Legal Name",
   "read_only": 1
  },
  {
   "fetch_from": "customer.client_code",
   "fieldname": "client_code",
   "fieldtype": "Data",
   "label": "Client Code",
   "read_only": 1
  },
  {
   "fetch_from": "customer.status",
   "fieldname": "customer_status",
   "fieldtype": "Data",
   "label": "Customer Status",
   "read_only": 1
  }
 ],
 "idx": 0,
 "istable": 1,
 "links": [],
 "modified": "2026-05-19 00:00:00.000000",
 "modified_by": "Administrator",
 "module": "Kunal Enterprises",
 "name": "Sales Employee Assigned Customer",
 "owner": "Administrator",
 "permissions": [],
 "sort_field": "modified",
 "sort_order": "DESC",
 "states": []
}
